tests/threadloop/__init__.py
tests/threadloop/test_threadloop.py
threadloop/__init__.py
threadloop/exceptions.py
threadloop/threadloop.py
threadloop-1.0.1.dist-info/DESCRIPTION.rst
threadloop-1.0.1.dist-info/METADATA
threadloop-1.0.1.dist-info/metadata.json
threadloop-1.0.1.dist-info/RECORD
threadloop-1.0.1.dist-info/top_level.txt
threadloop-1.0.1.dist-info/WHEEL
