Metadata-Version: 2.0
Name: threadloop
Version: 1.0.1
Summary: Tornado IOLoop Backed Concurrent Futures
Home-page: https://github.com/breerly/threadloop
Author: Grayson Koonce
Author-email: breerly@gmail.com
License: MIT
Platform: UNKNOWN
Classifier: License :: OSI Approved :: MIT License
Classifier: Programming Language :: Python :: 2
Classifier: Programming Language :: Python :: 2.7
Classifier: Programming Language :: Python :: 3
Classifier: Programming Language :: Python :: 3.3
Classifier: Programming Language :: Python :: 3.4
Classifier: Programming Language :: Python :: Implementation :: CPython
Classifier: Programming Language :: Python :: Implementation :: PyPy
Requires-Dist: tornado
